gmusicapi_wrapper/__init__.py
gmusicapi_wrapper/base.py
gmusicapi_wrapper/constants.py
gmusicapi_wrapper/decorators.py
gmusicapi_wrapper/mobileclient.py
gmusicapi_wrapper/musicmanager.py
gmusicapi_wrapper/utils.py
gmusicapi_wrapper-0.5.2.dist-info/DESCRIPTION.rst
gmusicapi_wrapper-0.5.2.dist-info/METADATA
gmusicapi_wrapper-0.5.2.dist-info/RECORD
gmusicapi_wrapper-0.5.2.dist-info/WHEEL
gmusicapi_wrapper-0.5.2.dist-info/metadata.json
gmusicapi_wrapper-0.5.2.dist-info/top_level.txt
