Metadata-Version: 2.0
Name: gmusicapi-wrapper
Version: 0.5.2
Summary: A wrapper interface around gmusicapi.
Home-page: https://github.com/thebigmunch/gmusicapi-wrapper
Author: thebigmunch
Author-email: mail@thebigmunch.me
License: MIT
Platform: UNKNOWN
Classifier: License :: OSI Approved :: MIT License
Classifier: Programming Language :: Python :: 3
Classifier: Programming Language :: Python :: 3.4
Classifier: Programming Language :: Python :: 3.5
Requires-Dist: gmusicapi (>=10.0.0)
Requires-Dist: mutagen (>=1.33)
Requires-Dist: wrapt
